st_screen_resolution/__init__.py
st_screen_resolution/frontend/build/asset-manifest.json
st_screen_resolution/frontend/build/bootstrap.min.css
st_screen_resolution/frontend/build/index.html
st_screen_resolution/frontend/build/static/js/2.409ed399.chunk.js
st_screen_resolution/frontend/build/static/js/2.409ed399.chunk.js.LICENSE.txt
st_screen_resolution/frontend/build/static/js/2.409ed399.chunk.js.map
st_screen_resolution/frontend/build/static/js/main.1a50ca2c.chunk.js
st_screen_resolution/frontend/build/static/js/main.1a50ca2c.chunk.js.map
st_screen_resolution/frontend/build/static/js/main.cba499ab.chunk.js
st_screen_resolution/frontend/build/static/js/main.cba499ab.chunk.js.map
st_screen_resolution/frontend/build/static/js/runtime-main.0f051bbb.js
st_screen_resolution/frontend/build/static/js/runtime-main.0f051bbb.js.map
st_screen_resolution-0.0.6.dist-info/LICENSE
st_screen_resolution-0.0.6.dist-info/METADATA
st_screen_resolution-0.0.6.dist-info/WHEEL
st_screen_resolution-0.0.6.dist-info/top_level.txt
st_screen_resolution-0.0.6.dist-info/RECORD
