Metadata-Version: 2.1
Name: st-screen-resolution
Version: 0.0.6
Summary: UNKNOWN
Home-page: UNKNOWN
Author: YM
Author-email: 
License: UNKNOWN
Platform: UNKNOWN
Requires-Python: >=3.6
License-File: LICENSE
Requires-Dist: streamlit (>=0.63)
